<core:FragmentDefinition xmlns="sap.m" xmlns:layout="sap.ui.layout" xmlns:form="sap.ui.layout.form" xmlns:micro="sap.suite.ui.commons" xmlns:core="sap.ui.core">
    <form:SimpleForm maxContainerCols="2" editable="false" layout="ResponsiveGridLayout" labelSpanL="12" labelSpanM="12" emptySpanL="0" emptySpanM="0" columnsL="1" columnsM="1">
        <form:content>
            <Label text="Contact Type" />
            <Text text="{products>ProductId}" />
            <Label text="Primary Contact Name" />
            <Text text="{products>Description}" />
            <Label text="Designation" />
            <Text text="{products>SupplierName}" />
            <Label text="Email" />
            <Text text="{products>SupplierName}" />
            <Label text="Phone" />
            <Text text="{products>SupplierName}" />
            <Label text="Fax" />
            <Text text="{products>SupplierName}" />
            <Label text="Extension" />
            <Text text="{products>SupplierName}" />
        </form:content>
    </form:SimpleForm>
</core:FragmentDefinition>
